otelanalyzer.so
otelanalyzer-1.0.5.dist-info/METADATA
otelanalyzer-1.0.5.dist-info/WHEEL
otelanalyzer-1.0.5.dist-info/top_level.txt
otelanalyzer-1.0.5.dist-info/RECORD
